gtfs2series/__init__.py
gtfs2series/gtfs.py
gtfs2series/series.py
gtfs2series-0.0.0.dist-info/METADATA
gtfs2series-0.0.0.dist-info/WHEEL
gtfs2series-0.0.0.dist-info/top_level.txt
gtfs2series-0.0.0.dist-info/RECORD
